bitoptions/__init__.py
bitoptions/fields.py
bitoptions/forms.py
bitoptions/lookups.py
bitoptions/utils.py
bitoptions/widgets.py
django_bitoptions-1.1.1.dist-info/LICENSE
django_bitoptions-1.1.1.dist-info/METADATA
django_bitoptions-1.1.1.dist-info/WHEEL
django_bitoptions-1.1.1.dist-info/top_level.txt
django_bitoptions-1.1.1.dist-info/RECORD
